arrotechtools/__init__.py
arrotechtools/auth.py
arrotechtools/serializer.py
arrotechtools/validator.py
arrotechtools-1.9.dist-info/LICENCE.txt
arrotechtools-1.9.dist-info/METADATA
arrotechtools-1.9.dist-info/WHEEL
arrotechtools-1.9.dist-info/top_level.txt
arrotechtools-1.9.dist-info/RECORD
