Metadata-Version: 2.1
Name: arrotechtools
Version: 1.9
Summary: Library with most of the useful methods in the world of programming
Home-page: UNKNOWN
Author: Harun Gachanja
Author-email: arrotechdesign@gmail.com
License: MIT
Keywords: roles
Platform: UNKNOWN
Classifier: Development Status :: 5 - Production/Stable
Classifier: Intended Audience :: Education
Classifier: Operating System :: OS Independent
Classifier: License :: OSI Approved :: MIT License
Classifier: Programming Language :: Python :: 3
Classifier: Programming Language :: Python :: 3.6
Classifier: Programming Language :: Python :: 3.7
License-File: LICENCE.txt
Requires-Dist: flask
Requires-Dist: flask-jwt-extended
